{
  "tournament": "ESL Pro League Season 19",
  "team_a": "Virtus.pro",
  "team_b": "The MongolZ",
  "status": "Ended",
  "start_time": "May 08, 2024 14:05",
  "link": "https://bo3.gg/matches/virtus-pro-vs-themongolz-08-05-2024",
  "match_id": "virtus-pro-vs-themongolz-08-05-2024",
  "game_count": 3,
  "game1": {
    "rounds": 24,
    "map": "overpass",
    "round_1": {
      "initial_team_a_econ": 4000,
      "initial_team_b_econ": 4000,
      "buy_team_a_econ": 600,
      "buy_team_b_econ": 750,
      "final_team_a_econ": 10900,
      "final_team_b_econ": 18500,
      "winner": "Team B",
      "win_type": "ace",
      "duration": 142,
      "team_a_buy_type": "Eco",
      "team_b_buy_type": "Eco",
      "score": "0-1",
      "players_alive_end": {
        "team_a": 0,
        "team_b": 0
      },
      "weapons_end": {
        "team_a": {
          "AK": 0,
          "M4": 0,
          "AWP": 0
        },
        "team_b": {
          "AK": 0,
          "M4": 0,
          "AWP": 0
        }
      },
      "kills_end": {
        "team_a": 3,
        "team_b": 5
      }
    },
    "round_2": {
      "initial_team_a_econ": 10900,
      "initial_team_b_econ": 18500,
      "buy_team_a_econ": 6700,
      "buy_team_b_econ": 500,
      "final_team_a_econ": 18900,
      "final_team_b_econ": 18900,
      "winner": "Team B",
      "win_type": "ace",
      "duration": 135,
      "team_a_buy_type": "Eco",
      "team_b_buy_type": "Semi",
      "score": "0-2",
      "players_alive_end": {
        "team_a": 0,
        "team_b": 0
      },
      "weapons_end": {
        "team_a": {
          "AK": 0,
          "M4": 0,
          "AWP": 0
        },
        "team_b": {
          "AK": 0,
          "M4": 2,
          "AWP": 0
        }
      },
      "kills_end": {
        "team_a": 1,
        "team_b": 5
      }
    },
    "round_3": {
      "initial_team_a_econ": 18900,
      "initial_team_b_econ": 18900,
      "buy_team_a_econ": 350,
      "buy_team_b_econ": 8950,
      "final_team_a_econ": 15500,
      "final_team_b_econ": 28000,
      "winner": "Team B",
      "win_type": "ace",
      "duration": 110,
      "team_a_buy_type": "Semi",
      "team_b_buy_type": "Force",
      "score": "0-3",
      "players_alive_end": {
        "team_a": 0,
        "team_b": 0
      },
      "weapons_end": {
        "team_a": {
          "AK": 0,
          "M4": 0,
          "AWP": 0
        },
        "team_b": {
          "AK": 1,
          "M4": 2,
          "AWP": 0
        }
      },
      "kills_end": {
        "team_a": 2,
        "team_b": 5
      }
    },
    "round_4": {
      "initial_team_a_econ": 15500,
      "initial_team_b_econ": 28000,
      "buy_team_a_econ": 5750,
      "buy_team_b_econ": 10450,
      "final_team_a_econ": 23400,
      "final_team_b_econ": 27700,
      "winner": "Team B",
      "win_type": "ace",
      "duration": 142,
      "team_a_buy_type": "Force",
      "team_b_buy_type": "Semi",
      "score": "0-4",
      "players_alive_end": {
        "team_a": 0,
        "team_b": 0
      },
      "weapons_end": {
        "team_a": {
          "AK": 0,
          "M4": 0,
          "AWP": 0
        },
        "team_b": {
          "AK": 2,
          "M4": 0,
          "AWP": 1
        }
      },
      "kills_end": {
        "team_a": 2,
        "team_b": 5
      }
    },
    "round_5": {
      "initial_team_a_econ": 23400,
      "initial_team_b_econ": 27700,
      "buy_team_a_econ": 450,
      "buy_team_b_econ": 13300,
      "final_team_a_econ": 18900,
      "final_team_b_econ": 20200,
      "winner": "Team A",
      "win_type": "explode",
      "duration": 127,
      "team_a_buy_type": "Full",
      "team_b_buy_type": "Semi",
      "score": "1-4",
      "players_alive_end": {
        "team_a": 0,
        "team_b": 0
      },
      "weapons_end": {
        "team_a": {
          "AK": 4,
          "M4": 0,
          "AWP": 1
        },
        "team_b": {
          "AK": 1,
          "M4": 2,
          "AWP": 0
        }
      },
      "kills_end": {
        "team_a": 2,
        "team_b": 0
      }
    },
    "round_6": {
      "initial_team_a_econ": 18900,
      "initial_team_b_econ": 20200,
      "buy_team_a_econ": 13500,
      "buy_team_b_econ": 6350,
      "final_team_a_econ": 31000,
      "final_team_b_econ": 16900,
      "winner": "Team A",
      "win_type": "ace",
      "duration": 141,
      "team_a_buy_type": "Force",
      "team_b_buy_type": "Semi",
      "score": "2-4",
      "players_alive_end": {
        "team_a": 0,
        "team_b": 0
      },
      "weapons_end": {
        "team_a": {
          "AK": 0,
          "M4": 0,
          "AWP": 1
        },
        "team_b": {
          "AK": 0,
          "M4": 0,
          "AWP": 0
        }
      },
      "kills_end": {
        "team_a": 5,
        "team_b": 4
      }
    },
    "round_7": {
      "initial_team_a_econ": 31000,
      "initial_team_b_econ": 16900,
      "buy_team_a_econ": 10100,
      "buy_team_b_econ": 600,
      "final_team_a_econ": 20300,
      "final_team_b_econ": 18400,
      "winner": "Team B",
      "win_type": "timeout",
      "duration": 147,
      "team_a_buy_type": "Full",
      "team_b_buy_type": "Semi",
      "score": "2-5",
      "players_alive_end": {
        "team_a": 0,
        "team_b": 0
      },
      "weapons_end": {
        "team_a": {
          "AK": 1,
          "M4": 0,
          "AWP": 0
        },
        "team_b": {
          "AK": 1,
          "M4": 2,
          "AWP": 0
        }
      },
      "kills_end": {
        "team_a": 2,
        "team_b": 4
      }
    },
    "round_8": {
      "initial_team_a_econ": 20300,
      "initial_team_b_econ": 18400,
      "buy_team_a_econ": 1250,
      "buy_team_b_econ": 4150,
      "final_team_a_econ": 19200,
      "final_team_b_econ": 11700,
      "winner": "Team A",
      "win_type": "ace",
      "duration": 150,
      "team_a_buy_type": "Semi",
      "team_b_buy_type": "Semi",
      "score": "3-5",
      "players_alive_end": {
        "team_a": 0,
        "team_b": 0
      },
      "weapons_end": {
        "team_a": {
          "AK": 1,
          "M4": 0,
          "AWP": 1
        },
        "team_b": {
          "AK": 0,
          "M4": 0,
          "AWP": 0
        }
      },
      "kills_end": {
        "team_a": 5,
        "team_b": 2
      }
    },
    "round_9": {
      "initial_team_a_econ": 19200,
      "initial_team_b_econ": 11700,
      "buy_team_a_econ": 8750,
      "buy_team_b_econ": 11700,
      "final_team_a_econ": 15800,
      "final_team_b_econ": 17500,
      "winner": "Team B",
      "win_type": "timeout",
      "duration": 189,
      "team_a_buy_type": "Semi",
      "team_b_buy_type": "Eco",
      "score": "3-6",
      "players_alive_end": {
        "team_a": 0,
        "team_b": 0
      },
      "weapons_end": {
        "team_a": {
          "AK": 1,
          "M4": 0,
          "AWP": 1
        },
        "team_b": {
          "AK": 0,
          "M4": 1,
          "AWP": 0
        }
      },
      "kills_end": {
        "team_a": 3,
        "team_b": 3
      }
    },
    "round_10": {
      "initial_team_a_econ": 15800,
      "initial_team_b_econ": 17500,
      "buy_team_a_econ": 15800,
      "buy_team_b_econ": 1750,
      "final_team_a_econ": 15000,
      "final_team_b_econ": 19200,
      "winner": "Team B",
      "win_type": "ace",
      "duration": 186,
      "team_a_buy_type": "Eco",
      "team_b_buy_type": "Semi",
      "score": "3-7",
      "players_alive_end": {
        "team_a": 0,
        "team_b": 0
      },
      "weapons_end": {
        "team_a": {
          "AK": 0,
          "M4": 0,
          "AWP": 0
        },
        "team_b": {
          "AK": 2,
          "M4": 1,
          "AWP": 1
        }
      },
      "kills_end": {
        "team_a": 0,
        "team_b": 5
      }
    },
    "round_11": {
      "initial_team_a_econ": 15000,
      "initial_team_b_econ": 19200,
      "buy_team_a_econ": 6350,
      "buy_team_b_econ": 11700,
      "final_team_a_econ": 20900,
      "final_team_b_econ": 29500,
      "winner": "Team B",
      "win_type": "ace",
      "duration": 145,
      "team_a_buy_type": "Force",
      "team_b_buy_type": "Force",
      "score": "3-8",
      "players_alive_end": {
        "team_a": 0,
        "team_b": 0
      },
      "weapons_end": {
        "team_a": {
          "AK": 0,
          "M4": 0,
          "AWP": 0
        },
        "team_b": {
          "AK": 3,
          "M4": 0,
          "AWP": 1
        }
      },
      "kills_end": {
        "team_a": 0,
        "team_b": 5
      }
    },
    "round_12": {
      "initial_team_a_econ": 20900,
      "initial_team_b_econ": 29500,
      "buy_team_a_econ": 1150,
      "buy_team_b_econ": 18100,
      "final_team_a_econ": 18800,
      "final_team_b_econ": 35900,
      "winner": "Team B",
      "win_type": "ace",
      "duration": 113,
      "team_a_buy_type": "Semi",
      "team_b_buy_type": "Semi",
      "score": "3-9",
      "players_alive_end": {
        "team_a": 0,
        "team_b": 0
      },
      "weapons_end": {
        "team_a": {
          "AK": 0,
          "M4": 0,
          "AWP": 0
        },
        "team_b": {
          "AK": 0,
          "M4": 0,
          "AWP": 0
        }
      },
      "kills_end": {
        "team_a": 2,
        "team_b": 5
      }
    },
    "round_13": {
      "initial_team_a_econ": 4000,
      "initial_team_b_econ": 4000,
      "buy_team_a_econ": 18400,
      "buy_team_b_econ": 10400,
      "final_team_a_econ": 18400,
      "final_team_b_econ": 10400,
      "winner": "Team A",
      "win_type": "ace",
      "duration": 327,
      "team_a_buy_type": "",
      "team_b_buy_type": "",
      "score": "4-9",
      "players_alive_end": {
        "team_a": 0,
        "team_b": 0
      },
      "weapons_end": {
        "team_a": {
          "AK": 0,
          "M4": 0,
          "AWP": 0
        },
        "team_b": {
          "AK": 0,
          "M4": 0,
          "AWP": 0
        }
      },
      "kills_end": {
        "team_a": 5,
        "team_b": 1
      }
    },
    "round_14": {
      "initial_team_a_econ": 18400,
      "initial_team_b_econ": 10400,
      "buy_team_a_econ": 2400,
      "buy_team_b_econ": 9800,
      "final_team_a_econ": 21200,
      "final_team_b_econ": 22000,
      "winner": "Team A",
      "win_type": "ace",
      "duration": 103,
      "team_a_buy_type": "Semi",
      "team_b_buy_type": "Eco",
      "score": "5-9",
      "players_alive_end": {
        "team_a": 0,
        "team_b": 0
      },
      "weapons_end": {
        "team_a": {
          "AK": 0,
          "M4": 2,
          "AWP": 0
        },
        "team_b": {
          "AK": 0,
          "M4": 0,
          "AWP": 0
        }
      },
      "kills_end": {
        "team_a": 5,
        "team_b": 0
      }
    },
    "round_15": {
      "initial_team_a_econ": 21200,
      "initial_team_b_econ": 22000,
      "buy_team_a_econ": 9950,
      "buy_team_b_econ": 500,
      "final_team_a_econ": 26800,
      "final_team_b_econ": 12050,
      "winner": "Team A",
      "win_type": "timeout",
      "duration": 151,
      "team_a_buy_type": "Semi",
      "team_b_buy_type": "Full",
      "score": "6-9",
      "players_alive_end": {
        "team_a": 0,
        "team_b": 0
      },
      "weapons_end": {
        "team_a": {
          "AK": 3,
          "M4": 1,
          "AWP": 1
        },
        "team_b": {
          "AK": 1,
          "M4": 0,
          "AWP": 0
        }
      },
      "kills_end": {
        "team_a": 4,
        "team_b": 0
      }
    },
    "round_16": {
      "initial_team_a_econ": 26800,
      "initial_team_b_econ": 12050,
      "buy_team_a_econ": 21600,
      "buy_team_b_econ": 6550,
      "final_team_a_econ": 29300,
      "final_team_b_econ": 24700,
      "winner": "Team B",
      "win_type": "ace",
      "duration": 106,
      "team_a_buy_type": "Force",
      "team_b_buy_type": "Force",
      "score": "6-10",
      "players_alive_end": {
        "team_a": 0,
        "team_b": 0
      },
      "weapons_end": {
        "team_a": {
          "AK": 0,
          "M4": 0,
          "AWP": 0
        },
        "team_b": {
          "AK": 2,
          "M4": 0,
          "AWP": 1
        }
      },
      "kills_end": {
        "team_a": 2,
        "team_b": 5
      }
    },
    "round_17": {
      "initial_team_a_econ": 29300,
      "initial_team_b_econ": 24700,
      "buy_team_a_econ": 29300,
      "buy_team_b_econ": 10800,
      "final_team_a_econ": 19700,
      "final_team_b_econ": 23000,
      "winner": "Team A",
      "win_type": "ace",
      "duration": 191,
      "team_a_buy_type": "Eco",
      "team_b_buy_type": "Semi",
      "score": "7-10",
      "players_alive_end": {
        "team_a": 0,
        "team_b": 0
      },
      "weapons_end": {
        "team_a": {
          "AK": 1,
          "M4": 1,
          "AWP": 1
        },
        "team_b": {
          "AK": 0,
          "M4": 0,
          "AWP": 0
        }
      },
      "kills_end": {
        "team_a": 5,
        "team_b": 2
      }
    },
    "round_18": {
      "initial_team_a_econ": 19700,
      "initial_team_b_econ": 23000,
      "buy_team_a_econ": 4150,
      "buy_team_b_econ": 1700,
      "final_team_a_econ": 11100,
      "final_team_b_econ": 20200,
      "winner": "Team B",
      "win_type": "explode",
      "duration": 149,
      "team_a_buy_type": "Semi",
      "team_b_buy_type": "Full",
      "score": "7-11",
      "players_alive_end": {
        "team_a": 0,
        "team_b": 0
      },
      "weapons_end": {
        "team_a": {
          "AK": 0,
          "M4": 3,
          "AWP": 0
        },
        "team_b": {
          "AK": 3,
          "M4": 0,
          "AWP": 1
        }
      },
      "kills_end": {
        "team_a": 0,
        "team_b": 2
      }
    },
    "round_19": {
      "initial_team_a_econ": 11100,
      "initial_team_b_econ": 20200,
      "buy_team_a_econ": 1200,
      "buy_team_b_econ": 12550,
      "final_team_a_econ": 18700,
      "final_team_b_econ": 20000,
      "winner": "Team A",
      "win_type": "timeout",
      "duration": 149,
      "team_a_buy_type": "Force",
      "team_b_buy_type": "Force",
      "score": "8-11",
      "players_alive_end": {
        "team_a": 0,
        "team_b": 0
      },
      "weapons_end": {
        "team_a": {
          "AK": 3,
          "M4": 1,
          "AWP": 0
        },
        "team_b": {
          "AK": 0,
          "M4": 0,
          "AWP": 1
        }
      },
      "kills_end": {
        "team_a": 4,
        "team_b": 1
      }
    },
    "round_20": {
      "initial_team_a_econ": 18700,
      "initial_team_b_econ": 20000,
      "buy_team_a_econ": 7550,
      "buy_team_b_econ": 5900,
      "final_team_a_econ": 14900,
      "final_team_b_econ": 20600,
      "winner": "Team B",
      "win_type": "ace",
      "duration": 147,
      "team_a_buy_type": "Semi",
      "team_b_buy_type": "Semi",
      "score": "8-12",
      "players_alive_end": {
        "team_a": 0,
        "team_b": 0
      },
      "weapons_end": {
        "team_a": {
          "AK": 0,
          "M4": 0,
          "AWP": 0
        },
        "team_b": {
          "AK": 2,
          "M4": 0,
          "AWP": 1
        }
      },
      "kills_end": {
        "team_a": 2,
        "team_b": 5
      }
    },
    "round_21": {
      "initial_team_a_econ": 14900,
      "initial_team_b_econ": 20600,
      "buy_team_a_econ": 1300,
      "buy_team_b_econ": 6250,
      "final_team_a_econ": 18200,
      "final_team_b_econ": 15100,
      "winner": "Team A",
      "win_type": "ace",
      "duration": 192,
      "team_a_buy_type": "Semi",
      "team_b_buy_type": "Semi",
      "score": "9-12",
      "players_alive_end": {
        "team_a": 0,
        "team_b": 0
      },
      "weapons_end": {
        "team_a": {
          "AK": 2,
          "M4": 0,
          "AWP": 0
        },
        "team_b": {
          "AK": 0,
          "M4": 0,
          "AWP": 0
        }
      },
      "kills_end": {
        "team_a": 5,
        "team_b": 3
      }
    },
    "round_22": {
      "initial_team_a_econ": 18200,
      "initial_team_b_econ": 15100,
      "buy_team_a_econ": 8700,
      "buy_team_b_econ": 15100,
      "final_team_a_econ": 19600,
      "final_team_b_econ": 9600,
      "winner": "Team A",
      "win_type": "ace",
      "duration": 195,
      "team_a_buy_type": "Force",
      "team_b_buy_type": "Eco",
      "score": "10-12",
      "players_alive_end": {
        "team_a": 0,
        "team_b": 0
      },
      "weapons_end": {
        "team_a": {
          "AK": 4,
          "M4": 0,
          "AWP": 0
        },
        "team_b": {
          "AK": 0,
          "M4": 0,
          "AWP": 0
        }
      },
      "kills_end": {
        "team_a": 5,
        "team_b": 0
      }
    },
    "round_23": {
      "initial_team_a_econ": 19600,
      "initial_team_b_econ": 9600,
      "buy_team_a_econ": 8300,
      "buy_team_b_econ": 9600,
      "final_team_a_econ": 26000,
      "final_team_b_econ": 22000,
      "winner": "Team A",
      "win_type": "ace",
      "duration": 75,
      "team_a_buy_type": "Semi",
      "team_b_buy_type": "Eco",
      "score": "11-12",
      "players_alive_end": {
        "team_a": 0,
        "team_b": 0
      },
      "weapons_end": {
        "team_a": {
          "AK": 3,
          "M4": 1,
          "AWP": 0
        },
        "team_b": {
          "AK": 0,
          "M4": 0,
          "AWP": 0
        }
      },
      "kills_end": {
        "team_a": 5,
        "team_b": 1
      }
    },
    "round_24": {
      "initial_team_a_econ": 26000,
      "initial_team_b_econ": 22000,
      "buy_team_a_econ": 14450,
      "buy_team_b_econ": 650,
      "final_team_a_econ": 15450,
      "final_team_b_econ": 2150,
      "winner": "Team B",
      "win_type": "ace",
      "duration": 154,
      "team_a_buy_type": "Semi",
      "team_b_buy_type": "Full",
      "score": "11-13",
      "players_alive_end": {
        "team_a": 0,
        "team_b": 0
      },
      "weapons_end": {
        "team_a": {
          "AK": 1,
          "M4": 0,
          "AWP": 0
        },
        "team_b": {
          "AK": 2,
          "M4": 0,
          "AWP": 0
        }
      },
      "kills_end": {
        "team_a": 3,
        "team_b": 4
      }
    }
  },
  "game2": {
    "rounds": 19,
    "map": "mirage",
    "round_1": {
      "initial_team_a_econ": 4000,
      "initial_team_b_econ": 3500,
      "buy_team_a_econ": 600,
      "buy_team_b_econ": 600,
      "final_team_a_econ": 11200,
      "final_team_b_econ": 19500,
      "winner": "Team B",
      "win_type": "explode",
      "duration": 139,
      "team_a_buy_type": "Eco",
      "team_b_buy_type": "Eco",
      "score": "0-1",
      "players_alive_end": {
        "team_a": 0,
        "team_b": 0
      },
      "weapons_end": {
        "team_a": {
          "AK": 0,
          "M4": 0,
          "AWP": 0
        },
        "team_b": {
          "AK": 0,
          "M4": 0,
          "AWP": 0
        }
      },
      "kills_end": {
        "team_a": 4,
        "team_b": 4
      }
    },
    "round_2": {
      "initial_team_a_econ": 11200,
      "initial_team_b_econ": 19500,
      "buy_team_a_econ": 550,
      "buy_team_b_econ": 1250,
      "final_team_a_econ": 12900,
      "final_team_b_econ": 19900,
      "winner": "Team B",
      "win_type": "explode",
      "duration": 129,
      "team_a_buy_type": "Semi",
      "team_b_buy_type": "Semi",
      "score": "0-2",
      "players_alive_end": {
        "team_a": 0,
        "team_b": 0
      },
      "weapons_end": {
        "team_a": {
          "AK": 0,
          "M4": 0,
          "AWP": 0
        },
        "team_b": {
          "AK": 1,
          "M4": 0,
          "AWP": 0
        }
      },
      "kills_end": {
        "team_a": 1,
        "team_b": 3
      }
    },
    "round_3": {
      "initial_team_a_econ": 12900,
      "initial_team_b_econ": 19900,
      "buy_team_a_econ": 10600,
      "buy_team_b_econ": 12200,
      "final_team_a_econ": 28400,
      "final_team_b_econ": 19800,
      "winner": "Team A",
      "win_type": "ace",
      "duration": 123,
      "team_a_buy_type": "Eco",
      "team_b_buy_type": "Force",
      "score": "1-2",
      "players_alive_end": {
        "team_a": 0,
        "team_b": 0
      },
      "weapons_end": {
        "team_a": {
          "AK": 1,
          "M4": 0,
          "AWP": 0
        },
        "team_b": {
          "AK": 0,
          "M4": 0,
          "AWP": 0
        }
      },
      "kills_end": {
        "team_a": 5,
        "team_b": 2
      }
    },
    "round_4": {
      "initial_team_a_econ": 28400,
      "initial_team_b_econ": 19800,
      "buy_team_a_econ": 11450,
      "buy_team_b_econ": 100,
      "final_team_a_econ": 21100,
      "final_team_b_econ": 19400,
      "winner": "Team B",
      "win_type": "explode",
      "duration": 146,
      "team_a_buy_type": "Semi",
      "team_b_buy_type": "Semi",
      "score": "1-3",
      "players_alive_end": {
        "team_a": 0,
        "team_b": 0
      },
      "weapons_end": {
        "team_a": {
          "AK": 0,
          "M4": 0,
          "AWP": 0
        },
        "team_b": {
          "AK": 2,
          "M4": 0,
          "AWP": 0
        }
      },
      "kills_end": {
        "team_a": 2,
        "team_b": 5
      }
    },
    "round_5": {
      "initial_team_a_econ": 21100,
      "initial_team_b_econ": 19400,
      "buy_team_a_econ": 800,
      "buy_team_b_econ": 6800,
      "final_team_a_econ": 18600,
      "final_team_b_econ": 14200,
      "winner": "Team A",
      "win_type": "ace",
      "duration": 137,
      "team_a_buy_type": "Full",
      "team_b_buy_type": "Semi",
      "score": "2-3",
      "players_alive_end": {
        "team_a": 0,
        "team_b": 0
      },
      "weapons_end": {
        "team_a": {
          "AK": 1,
          "M4": 1,
          "AWP": 1
        },
        "team_b": {
          "AK": 0,
          "M4": 0,
          "AWP": 0
        }
      },
      "kills_end": {
        "team_a": 5,
        "team_b": 1
      }
    },
    "round_6": {
      "initial_team_a_econ": 18600,
      "initial_team_b_econ": 14200,
      "buy_team_a_econ": 6750,
      "buy_team_b_econ": 1550,
      "final_team_a_econ": 24400,
      "final_team_b_econ": 9900,
      "winner": "Team A",
      "win_type": "ace",
      "duration": 84,
      "team_a_buy_type": "Semi",
      "team_b_buy_type": "Semi",
      "score": "3-3",
      "players_alive_end": {
        "team_a": 0,
        "team_b": 0
      },
      "weapons_end": {
        "team_a": {
          "AK": 2,
          "M4": 2,
          "AWP": 1
        },
        "team_b": {
          "AK": 0,
          "M4": 0,
          "AWP": 0
        }
      },
      "kills_end": {
        "team_a": 5,
        "team_b": 0
      }
    },
    "round_7": {
      "initial_team_a_econ": 24400,
      "initial_team_b_econ": 9900,
      "buy_team_a_econ": 16500,
      "buy_team_b_econ": 9900,
      "final_team_a_econ": 34400,
      "final_team_b_econ": 22000,
      "winner": "Team A",
      "win_type": "ace",
      "duration": 59,
      "team_a_buy_type": "Force",
      "team_b_buy_type": "Eco",
      "score": "4-3",
      "players_alive_end": {
        "team_a": 0,
        "team_b": 0
      },
      "weapons_end": {
        "team_a": {
          "AK": 2,
          "M4": 2,
          "AWP": 1
        },
        "team_b": {
          "AK": 0,
          "M4": 0,
          "AWP": 0
        }
      },
      "kills_end": {
        "team_a": 5,
        "team_b": 0
      }
    },
    "round_8": {
      "initial_team_a_econ": 34400,
      "initial_team_b_econ": 22000,
      "buy_team_a_econ": 32100,
      "buy_team_b_econ": 400,
      "final_team_a_econ": 49800,
      "final_team_b_econ": 15500,
      "winner": "Team A",
      "win_type": "ace",
      "duration": 129,
      "team_a_buy_type": "Eco",
      "team_b_buy_type": "Full",
      "score": "5-3",
      "players_alive_end": {
        "team_a": 0,
        "team_b": 0
      },
      "weapons_end": {
        "team_a": {
          "AK": 2,
          "M4": 0,
          "AWP": 1
        },
        "team_b": {
          "AK": 0,
          "M4": 0,
          "AWP": 0
        }
      },
      "kills_end": {
        "team_a": 5,
        "team_b": 2
      }
    },
    "round_9": {
      "initial_team_a_econ": 49100,
      "initial_team_b_econ": 15500,
      "buy_team_a_econ": 35500,
      "buy_team_b_econ": 9000,
      "final_team_a_econ": 53000,
      "final_team_b_econ": 26300,
      "winner": "Team A",
      "win_type": "ace",
      "duration": 57,
      "team_a_buy_type": "Semi",
      "team_b_buy_type": "Force",
      "score": "6-3",
      "players_alive_end": {
        "team_a": 0,
        "team_b": 0
      },
      "weapons_end": {
        "team_a": {
          "AK": 2,
          "M4": 1,
          "AWP": 1
        },
        "team_b": {
          "AK": 0,
          "M4": 0,
          "AWP": 0
        }
      },
      "kills_end": {
        "team_a": 5,
        "team_b": 1
      }
    },
    "round_10": {
      "initial_team_a_econ": 53000,
      "initial_team_b_econ": 26300,
      "buy_team_a_econ": 46200,
      "buy_team_b_econ": 5700,
      "final_team_a_econ": 65100,
      "final_team_b_econ": 23600,
      "winner": "Team A",
      "win_type": "defuse",
      "duration": 172,
      "team_a_buy_type": "Force",
      "team_b_buy_type": "Full",
      "score": "7-3",
      "players_alive_end": {
        "team_a": 0,
        "team_b": 0
      },
      "weapons_end": {
        "team_a": {
          "AK": 3,
          "M4": 0,
          "AWP": 0
        },
        "team_b": {
          "AK": 0,
          "M4": 0,
          "AWP": 0
        }
      },
      "kills_end": {
        "team_a": 5,
        "team_b": 2
      }
    },
    "round_11": {
      "initial_team_a_econ": 65100,
      "initial_team_b_econ": 23600,
      "buy_team_a_econ": 47800,
      "buy_team_b_econ": 400,
      "final_team_a_econ": 65400,
      "final_team_b_econ": 17700,
      "winner": "Team A",
      "win_type": "ace",
      "duration": 68,
      "team_a_buy_type": "Semi",
      "team_b_buy_type": "Full",
      "score": "8-3",
      "players_alive_end": {
        "team_a": 0,
        "team_b": 0
      },
      "weapons_end": {
        "team_a": {
          "AK": 4,
          "M4": 0,
          "AWP": 0
        },
        "team_b": {
          "AK": 0,
          "M4": 0,
          "AWP": 0
        }
      },
      "kills_end": {
        "team_a": 10,
        "team_b": 6
      }
    },
    "round_12": {
      "initial_team_a_econ": 65400,
      "initial_team_b_econ": 17700,
      "buy_team_a_econ": 51800,
      "buy_team_b_econ": 300,
      "final_team_a_econ": 68000,
      "final_team_b_econ": 18700,
      "winner": "Team A",
      "win_type": "ace",
      "duration": 98,
      "team_a_buy_type": "Semi",
      "team_b_buy_type": "Semi",
      "score": "9-3",
      "players_alive_end": {
        "team_a": 0,
        "team_b": 0
      },
      "weapons_end": {
        "team_a": {
          "AK": 0,
          "M4": 0,
          "AWP": 0
        },
        "team_b": {
          "AK": 0,
          "M4": 0,
          "AWP": 0
        }
      },
      "kills_end": {
        "team_a": 5,
        "team_b": 4
      }
    },
    "round_13": {
      "initial_team_a_econ": 4000,
      "initial_team_b_econ": 4000,
      "buy_team_a_econ": 18600,
      "buy_team_b_econ": 11100,
      "final_team_a_econ": 18600,
      "final_team_b_econ": 11100,
      "winner": "Team A",
      "win_type": "ace",
      "duration": 328,
      "team_a_buy_type": "",
      "team_b_buy_type": "",
      "score": "10-3",
      "players_alive_end": {
        "team_a": 0,
        "team_b": 0
      },
      "weapons_end": {
        "team_a": {
          "AK": 0,
          "M4": 0,
          "AWP": 0
        },
        "team_b": {
          "AK": 0,
          "M4": 0,
          "AWP": 0
        }
      },
      "kills_end": {
        "team_a": 5,
        "team_b": 3
      }
    },
    "round_14": {
      "initial_team_a_econ": 18600,
      "initial_team_b_econ": 11100,
      "buy_team_a_econ": 200,
      "buy_team_b_econ": 800,
      "final_team_a_econ": 7900,
      "final_team_b_econ": 19200,
      "winner": "Team B",
      "win_type": "ace",
      "duration": 85,
      "team_a_buy_type": "Semi",
      "team_b_buy_type": "Semi",
      "score": "10-4",
      "players_alive_end": {
        "team_a": 0,
        "team_b": 0
      },
      "weapons_end": {
        "team_a": {
          "AK": 0,
          "M4": 0,
          "AWP": 0
        },
        "team_b": {
          "AK": 1,
          "M4": 0,
          "AWP": 0
        }
      },
      "kills_end": {
        "team_a": 2,
        "team_b": 5
      }
    },
    "round_15": {
      "initial_team_a_econ": 7900,
      "initial_team_b_econ": 19200,
      "buy_team_a_econ": 6200,
      "buy_team_b_econ": 5100,
      "final_team_a_econ": 13800,
      "final_team_b_econ": 22600,
      "winner": "Team B",
      "win_type": "ace",
      "duration": 169,
      "team_a_buy_type": "Eco",
      "team_b_buy_type": "Semi",
      "score": "10-5",
      "players_alive_end": {
        "team_a": 0,
        "team_b": 0
      },
      "weapons_end": {
        "team_a": {
          "AK": 0,
          "M4": 0,
          "AWP": 0
        },
        "team_b": {
          "AK": 1,
          "M4": 2,
          "AWP": 0
        }
      },
      "kills_end": {
        "team_a": 0,
        "team_b": 5
      }
    },
    "round_16": {
      "initial_team_a_econ": 13800,
      "initial_team_b_econ": 22600,
      "buy_team_a_econ": 12600,
      "buy_team_b_econ": 17600,
      "final_team_a_econ": 29500,
      "final_team_b_econ": 36700,
      "winner": "Team B",
      "win_type": "defuse",
      "duration": 108,
      "team_a_buy_type": "Eco",
      "team_b_buy_type": "Eco",
      "score": "10-6",
      "players_alive_end": {
        "team_a": 0,
        "team_b": 0
      },
      "weapons_end": {
        "team_a": {
          "AK": 0,
          "M4": 1,
          "AWP": 0
        },
        "team_b": {
          "AK": 1,
          "M4": 1,
          "AWP": 0
        }
      },
      "kills_end": {
        "team_a": 2,
        "team_b": 4
      }
    },
    "round_17": {
      "initial_team_a_econ": 29500,
      "initial_team_b_econ": 37000,
      "buy_team_a_econ": 2750,
      "buy_team_b_econ": 21500,
      "final_team_a_econ": 21500,
      "final_team_b_econ": 29600,
      "winner": "Team A",
      "win_type": "explode",
      "duration": 141,
      "team_a_buy_type": "Full",
      "team_b_buy_type": "Semi",
      "score": "11-6",
      "players_alive_end": {
        "team_a": 0,
        "team_b": 0
      },
      "weapons_end": {
        "team_a": {
          "AK": 1,
          "M4": 0,
          "AWP": 1
        },
        "team_b": {
          "AK": 1,
          "M4": 0,
          "AWP": 0
        }
      },
      "kills_end": {
        "team_a": 4,
        "team_b": 3
      }
    },
    "round_18": {
      "initial_team_a_econ": 21500,
      "initial_team_b_econ": 29600,
      "buy_team_a_econ": 11450,
      "buy_team_b_econ": 6350,
      "final_team_a_econ": 23300,
      "final_team_b_econ": 15900,
      "winner": "Team A",
      "win_type": "ace",
      "duration": 206,
      "team_a_buy_type": "Semi",
      "team_b_buy_type": "Full",
      "score": "12-6",
      "players_alive_end": {
        "team_a": 0,
        "team_b": 0
      },
      "weapons_end": {
        "team_a": {
          "AK": 2,
          "M4": 0,
          "AWP": 1
        },
        "team_b": {
          "AK": 0,
          "M4": 0,
          "AWP": 0
        }
      },
      "kills_end": {
        "team_a": 5,
        "team_b": 2
      }
    },
    "round_19": {
      "initial_team_a_econ": 23300,
      "initial_team_b_econ": 15900,
      "buy_team_a_econ": 10650,
      "buy_team_b_econ": 100,
      "final_team_a_econ": 11950,
      "final_team_b_econ": 1300,
      "winner": "Team A",
      "win_type": "ace",
      "duration": 131,
      "team_a_buy_type": "Semi",
      "team_b_buy_type": "Semi",
      "score": "13-6",
      "players_alive_end": {
        "team_a": 0,
        "team_b": 0
      },
      "weapons_end": {
        "team_a": {
          "AK": 1,
          "M4": 0,
          "AWP": 0
        },
        "team_b": {
          "AK": 0,
          "M4": 0,
          "AWP": 0
        }
      },
      "kills_end": {
        "team_a": 4,
        "team_b": 4
      }
    }
  },
  "game3": {
    "rounds": 24,
    "map": "ancient",
    "round_1": {
      "initial_team_a_econ": 4000,
      "initial_team_b_econ": 4000,
      "buy_team_a_econ": 600,
      "buy_team_b_econ": 700,
      "final_team_a_econ": 19600,
      "final_team_b_econ": 11600,
      "winner": "Team A",
      "win_type": "explode",
      "duration": 129,
      "team_a_buy_type": "Eco",
      "team_b_buy_type": "Eco",
      "score": "1-0",
      "players_alive_end": {
        "team_a": 0,
        "team_b": 0
      },
      "weapons_end": {
        "team_a": {
          "AK": 0,
          "M4": 0,
          "AWP": 0
        },
        "team_b": {
          "AK": 0,
          "M4": 0,
          "AWP": 0
        }
      },
      "kills_end": {
        "team_a": 4,
        "team_b": 5
      }
    },
    "round_2": {
      "initial_team_a_econ": 19600,
      "initial_team_b_econ": 11600,
      "buy_team_a_econ": 600,
      "buy_team_b_econ": 550,
      "final_team_a_econ": 6950,
      "final_team_b_econ": 18700,
      "winner": "Team B",
      "win_type": "timeout",
      "duration": 148,
      "team_a_buy_type": "Semi",
      "team_b_buy_type": "Semi",
      "score": "1-1",
      "players_alive_end": {
        "team_a": 0,
        "team_b": 0
      },
      "weapons_end": {
        "team_a": {
          "AK": 0,
          "M4": 0,
          "AWP": 0
        },
        "team_b": {
          "AK": 1,
          "M4": 0,
          "AWP": 0
        }
      },
      "kills_end": {
        "team_a": 3,
        "team_b": 5
      }
    },
    "round_3": {
      "initial_team_a_econ": 6950,
      "initial_team_b_econ": 18700,
      "buy_team_a_econ": 200,
      "buy_team_b_econ": 3900,
      "final_team_a_econ": 9900,
      "final_team_b_econ": 21700,
      "winner": "Team B",
      "win_type": "ace",
      "duration": 85,
      "team_a_buy_type": "Force",
      "team_b_buy_type": "Semi",
      "score": "1-2",
      "players_alive_end": {
        "team_a": 0,
        "team_b": 0
      },
      "weapons_end": {
        "team_a": {
          "AK": 0,
          "M4": 0,
          "AWP": 0
        },
        "team_b": {
          "AK": 1,
          "M4": 1,
          "AWP": 0
        }
      },
      "kills_end": {
        "team_a": 1,
        "team_b": 5
      }
    },
    "round_4": {
      "initial_team_a_econ": 9900,
      "initial_team_b_econ": 21700,
      "buy_team_a_econ": 9000,
      "buy_team_b_econ": 9600,
      "final_team_a_econ": 21300,
      "final_team_b_econ": 27400,
      "winner": "Team B",
      "win_type": "ace",
      "duration": 63,
      "team_a_buy_type": "Eco",
      "team_b_buy_type": "Semi",
      "score": "1-3",
      "players_alive_end": {
        "team_a": 0,
        "team_b": 0
      },
      "weapons_end": {
        "team_a": {
          "AK": 0,
          "M4": 0,
          "AWP": 0
        },
        "team_b": {
          "AK": 1,
          "M4": 1,
          "AWP": 1
        }
      },
      "kills_end": {
        "team_a": 1,
        "team_b": 5
      }
    },
    "round_5": {
      "initial_team_a_econ": 21300,
      "initial_team_b_econ": 27400,
      "buy_team_a_econ": 400,
      "buy_team_b_econ": 19500,
      "final_team_a_econ": 15300,
      "final_team_b_econ": 37200,
      "winner": "Team B",
      "win_type": "ace",
      "duration": 95,
      "team_a_buy_type": "Full",
      "team_b_buy_type": "Force",
      "score": "1-4",
      "players_alive_end": {
        "team_a": 0,
        "team_b": 0
      },
      "weapons_end": {
        "team_a": {
          "AK": 0,
          "M4": 0,
          "AWP": 0
        },
        "team_b": {
          "AK": 2,
          "M4": 1,
          "AWP": 1
        }
      },
      "kills_end": {
        "team_a": 1,
        "team_b": 5
      }
    },
    "round_6": {
      "initial_team_a_econ": 15300,
      "initial_team_b_econ": 37200,
      "buy_team_a_econ": 15300,
      "buy_team_b_econ": 28900,
      "final_team_a_econ": 22100,
      "final_team_b_econ": 45800,
      "winner": "Team B",
      "win_type": "ace",
      "duration": 175,
      "team_a_buy_type": "Eco",
      "team_b_buy_type": "Force",
      "score": "1-5",
      "players_alive_end": {
        "team_a": 0,
        "team_b": 0
      },
      "weapons_end": {
        "team_a": {
          "AK": 0,
          "M4": 0,
          "AWP": 0
        },
        "team_b": {
          "AK": 2,
          "M4": 2,
          "AWP": 1
        }
      },
      "kills_end": {
        "team_a": 0,
        "team_b": 5
      }
    },
    "round_7": {
      "initial_team_a_econ": 22100,
      "initial_team_b_econ": 45800,
      "buy_team_a_econ": 1000,
      "buy_team_b_econ": 39800,
      "final_team_a_econ": 15450,
      "final_team_b_econ": 56800,
      "winner": "Team B",
      "win_type": "timeout",
      "duration": 151,
      "team_a_buy_type": "Full",
      "team_b_buy_type": "Force",
      "score": "1-6",
      "players_alive_end": {
        "team_a": 0,
        "team_b": 0
      },
      "weapons_end": {
        "team_a": {
          "AK": 1,
          "M4": 0,
          "AWP": 0
        },
        "team_b": {
          "AK": 1,
          "M4": 1,
          "AWP": 0
        }
      },
      "kills_end": {
        "team_a": 3,
        "team_b": 4
      }
    },
    "round_8": {
      "initial_team_a_econ": 15450,
      "initial_team_b_econ": 56800,
      "buy_team_a_econ": 7150,
      "buy_team_b_econ": 35700,
      "final_team_a_econ": 25800,
      "final_team_b_econ": 42800,
      "winner": "Team A",
      "win_type": "explode",
      "duration": 147,
      "team_a_buy_type": "Force",
      "team_b_buy_type": "Full",
      "score": "2-6",
      "players_alive_end": {
        "team_a": 0,
        "team_b": 0
      },
      "weapons_end": {
        "team_a": {
          "AK": 1,
          "M4": 2,
          "AWP": 1
        },
        "team_b": {
          "AK": 1,
          "M4": 1,
          "AWP": 0
        }
      },
      "kills_end": {
        "team_a": 3,
        "team_b": 0
      }
    },
    "round_9": {
      "initial_team_a_econ": 25800,
      "initial_team_b_econ": 42800,
      "buy_team_a_econ": 17600,
      "buy_team_b_econ": 21750,
      "final_team_a_econ": 30000,
      "final_team_b_econ": 39300,
      "winner": "Team B",
      "win_type": "timeout",
      "duration": 150,
      "team_a_buy_type": "Force",
      "team_b_buy_type": "Full",
      "score": "2-7",
      "players_alive_end": {
        "team_a": 0,
        "team_b": 0
      },
      "weapons_end": {
        "team_a": {
          "AK": 0,
          "M4": 1,
          "AWP": 0
        },
        "team_b": {
          "AK": 1,
          "M4": 0,
          "AWP": 1
        }
      },
      "kills_end": {
        "team_a": 3,
        "team_b": 4
      }
    },
    "round_10": {
      "initial_team_a_econ": 30000,
      "initial_team_b_econ": 39300,
      "buy_team_a_econ": 8000,
      "buy_team_b_econ": 20800,
      "final_team_a_econ": 25100,
      "final_team_b_econ": 38300,
      "winner": "Team B",
      "win_type": "ace",
      "duration": 142,
      "team_a_buy_type": "Full",
      "team_b_buy_type": "Semi",
      "score": "2-8",
      "players_alive_end": {
        "team_a": 0,
        "team_b": 0
      },
      "weapons_end": {
        "team_a": {
          "AK": 0,
          "M4": 0,
          "AWP": 0
        },
        "team_b": {
          "AK": 1,
          "M4": 0,
          "AWP": 1
        }
      },
      "kills_end": {
        "team_a": 3,
        "team_b": 5
      }
    },
    "round_11": {
      "initial_team_a_econ": 25100,
      "initial_team_b_econ": 38300,
      "buy_team_a_econ": 1750,
      "buy_team_b_econ": 19600,
      "final_team_a_econ": 18700,
      "final_team_b_econ": 37400,
      "winner": "Team B",
      "win_type": "ace",
      "duration": 145,
      "team_a_buy_type": "Full",
      "team_b_buy_type": "Semi",
      "score": "2-9",
      "players_alive_end": {
        "team_a": 0,
        "team_b": 0
      },
      "weapons_end": {
        "team_a": {
          "AK": 0,
          "M4": 0,
          "AWP": 0
        },
        "team_b": {
          "AK": 3,
          "M4": 1,
          "AWP": 1
        }
      },
      "kills_end": {
        "team_a": 0,
        "team_b": 5
      }
    },
    "round_12": {
      "initial_team_a_econ": 18700,
      "initial_team_b_econ": 37400,
      "buy_team_a_econ": 1000,
      "buy_team_b_econ": 27400,
      "final_team_a_econ": 17800,
      "final_team_b_econ": 45200,
      "winner": "Team B",
      "win_type": "ace",
      "duration": 91,
      "team_a_buy_type": "Semi",
      "team_b_buy_type": "Force",
      "score": "2-10",
      "players_alive_end": {
        "team_a": 0,
        "team_b": 0
      },
      "weapons_end": {
        "team_a": {
          "AK": 0,
          "M4": 0,
          "AWP": 0
        },
        "team_b": {
          "AK": 0,
          "M4": 0,
          "AWP": 0
        }
      },
      "kills_end": {
        "team_a": 0,
        "team_b": 5
      }
    },
    "round_13": {
      "initial_team_a_econ": 4000,
      "initial_team_b_econ": 4000,
      "buy_team_a_econ": 4000,
      "buy_team_b_econ": 2700,
      "final_team_a_econ": 10900,
      "final_team_b_econ": 18800,
      "winner": "Team B",
      "win_type": "ace",
      "duration": 336,
      "team_a_buy_type": "Eco",
      "team_b_buy_type": "Eco",
      "score": "2-11",
      "players_alive_end": {
        "team_a": 0,
        "team_b": 0
      },
      "weapons_end": {
        "team_a": {
          "AK": 0,
          "M4": 0,
          "AWP": 0
        },
        "team_b": {
          "AK": 0,
          "M4": 0,
          "AWP": 0
        }
      },
      "kills_end": {
        "team_a": 3,
        "team_b": 5
      }
    },
    "round_14": {
      "initial_team_a_econ": 10900,
      "initial_team_b_econ": 18800,
      "buy_team_a_econ": 500,
      "buy_team_b_econ": 550,
      "final_team_a_econ": 19400,
      "final_team_b_econ": 8800,
      "winner": "Team A",
      "win_type": "ace",
      "duration": 140,
      "team_a_buy_type": "Semi",
      "team_b_buy_type": "Semi",
      "score": "3-11",
      "players_alive_end": {
        "team_a": 0,
        "team_b": 0
      },
      "weapons_end": {
        "team_a": {
          "AK": 1,
          "M4": 0,
          "AWP": 0
        },
        "team_b": {
          "AK": 0,
          "M4": 0,
          "AWP": 0
        }
      },
      "kills_end": {
        "team_a": 5,
        "team_b": 4
      }
    },
    "round_15": {
      "initial_team_a_econ": 19400,
      "initial_team_b_econ": 8800,
      "buy_team_a_econ": 1100,
      "buy_team_b_econ": 300,
      "final_team_a_econ": 20800,
      "final_team_b_econ": 14600,
      "winner": "Team A",
      "win_type": "defuse",
      "duration": 159,
      "team_a_buy_type": "Semi",
      "team_b_buy_type": "Force",
      "score": "4-11",
      "players_alive_end": {
        "team_a": 0,
        "team_b": 0
      },
      "weapons_end": {
        "team_a": {
          "AK": 1,
          "M4": 2,
          "AWP": 0
        },
        "team_b": {
          "AK": 0,
          "M4": 0,
          "AWP": 0
        }
      },
      "kills_end": {
        "team_a": 5,
        "team_b": 2
      }
    },
    "round_16": {
      "initial_team_a_econ": 20800,
      "initial_team_b_econ": 14600,
      "buy_team_a_econ": 7800,
      "buy_team_b_econ": 550,
      "final_team_a_econ": 24600,
      "final_team_b_econ": 17200,
      "winner": "Team A",
      "win_type": "defuse",
      "duration": 132,
      "team_a_buy_type": "Semi",
      "team_b_buy_type": "Semi",
      "score": "5-11",
      "players_alive_end": {
        "team_a": 0,
        "team_b": 0
      },
      "weapons_end": {
        "team_a": {
          "AK": 1,
          "M4": 2,
          "AWP": 0
        },
        "team_b": {
          "AK": 0,
          "M4": 0,
          "AWP": 0
        }
      },
      "kills_end": {
        "team_a": 5,
        "team_b": 2
      }
    },
    "round_17": {
      "initial_team_a_econ": 24600,
      "initial_team_b_econ": 17200,
      "buy_team_a_econ": 9250,
      "buy_team_b_econ": 8700,
      "final_team_a_econ": 27000,
      "final_team_b_econ": 24400,
      "winner": "Team A",
      "win_type": "ace",
      "duration": 87,
      "team_a_buy_type": "Semi",
      "team_b_buy_type": "Force",
      "score": "6-11",
      "players_alive_end": {
        "team_a": 0,
        "team_b": 0
      },
      "weapons_end": {
        "team_a": {
          "AK": 0,
          "M4": 0,
          "AWP": 1
        },
        "team_b": {
          "AK": 0,
          "M4": 0,
          "AWP": 0
        }
      },
      "kills_end": {
        "team_a": 5,
        "team_b": 4
      }
    },
    "round_18": {
      "initial_team_a_econ": 27000,
      "initial_team_b_econ": 24400,
      "buy_team_a_econ": 5650,
      "buy_team_b_econ": 800,
      "final_team_a_econ": 22900,
      "final_team_b_econ": 18200,
      "winner": "Team A",
      "win_type": "ace",
      "duration": 111,
      "team_a_buy_type": "Full",
      "team_b_buy_type": "Full",
      "score": "7-11",
      "players_alive_end": {
        "team_a": 0,
        "team_b": 0
      },
      "weapons_end": {
        "team_a": {
          "AK": 0,
          "M4": 2,
          "AWP": 1
        },
        "team_b": {
          "AK": 0,
          "M4": 0,
          "AWP": 0
        }
      },
      "kills_end": {
        "team_a": 5,
        "team_b": 2
      }
    },
    "round_19": {
      "initial_team_a_econ": 22900,
      "initial_team_b_econ": 18200,
      "buy_team_a_econ": 6650,
      "buy_team_b_econ": 17100,
      "final_team_a_econ": 24900,
      "final_team_b_econ": 29800,
      "winner": "Team A",
      "win_type": "defuse",
      "duration": 204,
      "team_a_buy_type": "Semi",
      "team_b_buy_type": "Eco",
      "score": "8-11",
      "players_alive_end": {
        "team_a": 0,
        "team_b": 0
      },
      "weapons_end": {
        "team_a": {
          "AK": 0,
          "M4": 0,
          "AWP": 1
        },
        "team_b": {
          "AK": 0,
          "M4": 0,
          "AWP": 0
        }
      },
      "kills_end": {
        "team_a": 4,
        "team_b": 4
      }
    },
    "round_20": {
      "initial_team_a_econ": 24900,
      "initial_team_b_econ": 29800,
      "buy_team_a_econ": 4150,
      "buy_team_b_econ": 4650,
      "final_team_a_econ": 22900,
      "final_team_b_econ": 26900,
      "winner": "Team A",
      "win_type": "defuse",
      "duration": 160,
      "team_a_buy_type": "Full",
      "team_b_buy_type": "Full",
      "score": "9-11",
      "players_alive_end": {
        "team_a": 0,
        "team_b": 0
      },
      "weapons_end": {
        "team_a": {
          "AK": 1,
          "M4": 0,
          "AWP": 1
        },
        "team_b": {
          "AK": 0,
          "M4": 0,
          "AWP": 0
        }
      },
      "kills_end": {
        "team_a": 5,
        "team_b": 3
      }
    },
    "round_21": {
      "initial_team_a_econ": 22900,
      "initial_team_b_econ": 26900,
      "buy_team_a_econ": 17200,
      "buy_team_b_econ": 4000,
      "final_team_a_econ": 21300,
      "final_team_b_econ": 18400,
      "winner": "Team A",
      "win_type": "ace",
      "duration": 137,
      "team_a_buy_type": "Force",
      "team_b_buy_type": "Full",
      "score": "10-11",
      "players_alive_end": {
        "team_a": 0,
        "team_b": 0
      },
      "weapons_end": {
        "team_a": {
          "AK": 3,
          "M4": 0,
          "AWP": 1
        },
        "team_b": {
          "AK": 0,
          "M4": 0,
          "AWP": 0
        }
      },
      "kills_end": {
        "team_a": 5,
        "team_b": 1
      }
    },
    "round_22": {
      "initial_team_a_econ": 21300,
      "initial_team_b_econ": 18400,
      "buy_team_a_econ": 12050,
      "buy_team_b_econ": 8300,
      "final_team_a_econ": 31100,
      "final_team_b_econ": 30900,
      "winner": "Team A",
      "win_type": "defuse",
      "duration": 119,
      "team_a_buy_type": "Force",
      "team_b_buy_type": "Semi",
      "score": "11-11",
      "players_alive_end": {
        "team_a": 0,
        "team_b": 0
      },
      "weapons_end": {
        "team_a": {
          "AK": 0,
          "M4": 0,
          "AWP": 1
        },
        "team_b": {
          "AK": 0,
          "M4": 0,
          "AWP": 0
        }
      },
      "kills_end": {
        "team_a": 5,
        "team_b": 4
      }
    },
    "round_23": {
      "initial_team_a_econ": 31100,
      "initial_team_b_econ": 30900,
      "buy_team_a_econ": 7400,
      "buy_team_b_econ": 4200,
      "final_team_a_econ": 26600,
      "final_team_b_econ": 26400,
      "winner": "Team A",
      "win_type": "defuse",
      "duration": 113,
      "team_a_buy_type": "Full",
      "team_b_buy_type": "Full",
      "score": "12-11",
      "players_alive_end": {
        "team_a": 0,
        "team_b": 0
      },
      "weapons_end": {
        "team_a": {
          "AK": 0,
          "M4": 1,
          "AWP": 0
        },
        "team_b": {
          "AK": 0,
          "M4": 0,
          "AWP": 0
        }
      },
      "kills_end": {
        "team_a": 5,
        "team_b": 3
      }
    },
    "round_24": {
      "initial_team_a_econ": 26600,
      "initial_team_b_econ": 26400,
      "buy_team_a_econ": 5300,
      "buy_team_b_econ": 1400,
      "final_team_a_econ": 5950,
      "final_team_b_econ": 1700,
      "winner": "Team A",
      "win_type": "ace",
      "duration": 55,
      "team_a_buy_type": "Full",
      "team_b_buy_type": "Full",
      "score": "13-11",
      "players_alive_end": {
        "team_a": 0,
        "team_b": 0
      },
      "weapons_end": {
        "team_a": {
          "AK": 0,
          "M4": 2,
          "AWP": 1
        },
        "team_b": {
          "AK": 1,
          "M4": 0,
          "AWP": 0
        }
      },
      "kills_end": {
        "team_a": 4,
        "team_b": 1
      }
    }
  }
}